{
    "Ar36": {
        "error": 1.7730782664810675e-08,
        "error_type": "",
        "fit": "previous",
        "references": [
            {
                "exclude": false,
                "record_id": "ba-01-n-8948"
            }
        ],
        "value": 3.9215382825396614e-07
    },
    "Ar37": {
        "error": 3.5227838745630316e-07,
        "error_type": "",
        "fit": "previous",
        "references": [
            {
                "exclude": false,
                "record_id": "ba-01-n-8948"
            }
        ],
        "value": 6.163369683510822e-08
    },
    "Ar38": {
        "error": 4.284110001591326e-07,
        "error_type": "",
        "fit": "previous",
        "references": [
            {
                "exclude": false,
                "record_id": "ba-01-n-8948"
            }
        ],
        "value": -1.509825947566758e-07
    },
    "Ar39": {
        "error": 3.699268367889479e-07,
        "error_type": "",
        "fit": "previous",
        "references": [
            {
                "exclude": false,
                "record_id": "ba-01-n-8948"
            }
        ],
        "value": 1.5408872780514485e-08
    },
    "Ar40": {
        "error": 2.9305922018462345e-06,
        "error_type": "",
        "fit": "previous",
        "references": [
            {
                "exclude": false,
                "record_id": "ba-01-n-8948"
            }
        ],
        "value": 7.272238959678621e-05
    }
}